<?xml version="1.0" encoding="UTF-8"?>
<sounds xmlns:xsi="http://www.w3.org/2001/XMLSchema-instance">
	<sound>
		<path>hit.mp3</path>
		<logicname>hit1</logicname>
	</sound>
	<sound>
		<path>hit2.mp3</path>
		<logicname>hit2</logicname>
	</sound>
	<sound>
		<path>hit3.mp3</path>
		<logicname>hit3</logicname>
	</sound>
	<sound>
		<path>glass.mp3</path>
		<logicname>error</logicname>
	</sound>
	<sound>
		<path>loginSong.mp3</path>
		<logicname>loginSong</logicname>
	</sound>
	<sound>
		<path>fireball.mp3</path>
		<logicname>fireball</logicname>
	</sound>
	<sound>
		<path>iceblock.mp3</path>
		<logicname>iceblock</logicname>
	</sound>
	<sound>
		<path>shot.mp3</path>
		<logicname>shot</logicname>
	</sound>
	<sound>
		<path>lightning.mp3</path>
		<logicname>lightning</logicname>
	</sound>
</sounds>